CHANGELOG.txt
LICENSE.txt
MANIFEST.in
README.md
setup.py
.ipynb_checkpoints/CHANGELOG-checkpoint.txt
.ipynb_checkpoints/LICENSE-checkpoint.txt
.ipynb_checkpoints/README-checkpoint.md
.ipynb_checkpoints/setup-checkpoint.py
src/adsorption.py
src/kinetics.py
src/.ipynb_checkpoints/adsorption-checkpoint.py
src/.ipynb_checkpoints/kinetics-checkpoint.py
src/chempy_ad.egg-info/SOURCES.txt
src/chempy_ad.egg-info/dependency_links.txt
src/chempy_ad.egg-info/top_level.txt
src/pychemeng.egg-info/PKG-INFO
src/pychemeng.egg-info/SOURCES.txt
src/pychemeng.egg-info/dependency_links.txt
src/pychemeng.egg-info/top_level.txt