Metadata-Version: 2.1
Name: pyChemEng
Version: 0.0.8
Summary: package for understanding adsorption isotherms and kinetics
Author: Ashane Fernando
Author-email: ashfern@yahoo.com
License: UNKNOWN
Platform: UNKNOWN
License-File: LICENSE.txt
